<?xml version="1.0" encoding="UTF-8" ?>
<!-- Remark -->
<ProfileLib ID="1100000" Name="ALL" Version="1.0" DefaultID="10001012" RecentLimited="20">
    <Category ID="1000000" Name="Common Video">
        <ProfileLnk ID="10001314" Name="AVI MSMPEG4-V3 (*.avi)" Comment="Can be played on every Windows PC" />
        <ProfileLnk ID="10001267" Name="DivX AVI - Audio Video Interleaved(DivX)(*.avi)" Comment="DivX Video Developed by open source organization,with fine sound quality and excellent picture quality" />
        <ProfileLnk ID="10001082" Name="Xvid AVI - Audio Video Interleaved(Xvid)(*.avi)" Comment="Xvid Video Developed by open source organization,with fine sound quality and excellent picture quality" />
        <ProfileLnk ID="10001315" Name="WMV3 (WMV9)(*.wmv)" Comment="High quality wmv with VC-1 codec" />
        <ProfileLnk ID="10001316" Name="WMV2 (WMV8)(*.wmv)" Comment="Fast conversion speed with wmv2 codec" />
        <ProfileLnk ID="10001317" Name="ASF (VC-1)(*.asf)" Comment="High quality asf with VC-1 codec" />
        <ProfileLnk ID="10001318" Name="MPEG-1 Video(*.mpg)" Comment="MPEG-1 Video profile optimized for television" />
        <ProfileLnk ID="10001319" Name="MPEG-2 Video(*.mpg)" Comment="MPEG-2 Video profile optimized for television" />
        <ProfileLnk ID="10001320" Name="H.264 Video(*.mp4)" Comment="H.264 Video configure" />
        <ProfileLnk ID="10001321" Name="3GPP ( H.263 / AMR)(*.3gp)" Comment="3GPP h.263 Video" />
        <ProfileLnk ID="10001322" Name="3GPP ( Xvid / AAC)(*.3gp)" Comment="3GPP MPEG-4 Video" />
        <ProfileLnk ID="10001323" Name="3GPP2 ( Xvid / AAC)(*.3g2)" Comment="3GPP2 MPEG-4 Video" />
        <ProfileLnk ID="10001075" Name="MPEG-4 Movie(*.mp4)" Comment="Compression standard for network broadcast and video comminication,with small size and high picture quality" />
        <ProfileLnk ID="10001067" Name="MOV - QuickTime(*.mov)" Comment="Apple QuickTime format" />
        <ProfileLnk ID="10001081" Name="MKV(Matroska) Video (*.mkv)" Comment='Stands for Matroska Video,it is described by its developers as&quot;the extensible open standard Audio/Video Container' />
        <ProfileLnk ID="10001068" Name="M4V - MPEG-4 Video(*.m4v)" Comment="MPEG-4 Video configure" />
        <!--ProfileLnk ID="10001076" Name="MP4 AVC(*.mp4)" Comment="H.264 Video configure" /-->
        <!--ProfileLnk ID="10001069" Name="MPEG-1 Movie - NTSC(*.mpg)" Comment="MPEG-1 Video profile optimized for television(NTSC)" /-->
        <!--ProfileLnk ID="10001070" Name="MPEG-1 Movie - PAL(*.mpg)" Comment="MPEG-1 Video profile optimized for television(PAL)" /-->
        <!--ProfileLnk ID="10001071" Name="MPEG-1 Movie - SECAM(*.mpg)" Comment="MPEG-1 Video profile optimized for television(SECAM)" /-->
        <!--ProfileLnk ID="10001072" Name="MPEG-2 Movie - NTSC(*.mpg)" Comment="MPEG-2 Video profile optimized for television(NTSC)" /-->
        <!--ProfileLnk ID="10001073" Name="MPEG-2 Movie - PAL(*.mpg)" Comment="MPEG-2 Video profile optimized for television(PAL)" /-->
        <!--ProfileLnk ID="10001074" Name="MPEG-2 Movie - SECAM(*.mpg)" Comment="MPEG-2 Video profile optimized for television(SECAM)" /-->
        <!--ProfileLnk ID="10001261" Name="Youtube Video(*.flv)" Comment="" /-->
        <!--ProfileLnk ID="10001262" Name="MPEG-2 Video profile optimized for television(NTSC)" Comment="" /-->
        <!--ProfileLnk ID="10001077" Name="WMV - Windows Media Video(*.wmv)" Comment="Stands for Windows Media Video,widely used for network transmission" /-->
    </Category>
    <Category ID="1000001" Name="Common Audio">
        <ProfileLnk ID="10001092" Name="MP3 - MPEG Layer-3 Audio(*.mp3)" Comment="A popular compression format used for audio files on computers and portable devices,with excellent sound quality and small size" />
        <ProfileLnk ID="10001097" Name="WAV - Waveform Audio(*.wav)" Comment="Microsoft audio format, with lossless sound quality and large file size" />
        <ProfileLnk ID="10001093" Name="M4A - MPEG-4 Audio(*.m4a)" Comment="Usually used MPEG-4 audio format,it can produce good audio quality using little physical space" />
        <ProfileLnk ID="10001098" Name="OGG - Ogg Vorbis Audio(*.ogg)" Comment="Audio format,support multi-channels with fine sound quality" />
        <ProfileLnk ID="10001094" Name="AC3 - Dolby Digital AC-3(*.ac3)" Comment="Digital audio format,support multi-channels and stereo sound" />
        <ProfileLnk ID="10001096" Name="WMA - Windows Media Audio(*.wma)" Comment="Stands for Windows Media Audio,popular audio format with low bitrate and fine sound quality" />
        <ProfileLnk ID="10001095" Name="AAC - Advanced Audio Coding(*.aac)" Comment="Advanced Audio Coding, a Lossy Compression format capable of delivering relatively high quality at relatively low bitrate" />
        <ProfileLnk ID="10001101" Name="SUN AU Format(*.au)" Comment="Digital audio format on Unix OS" />
        <ProfileLnk ID="10001224" Name="AIFF-Audio Interchange File Format(*.aiff)" Comment="An Apple Macintosh native file format for audio interchage,wildely used in professional audio applications" />
        <ProfileLnk ID="10001324" Name="MP2 Audio(*.mp2)" Comment="MPEG-1 Layer2 Audio" />
        <ProfileLnk ID="10001103" Name="FLAC-Free Lossless Audio Codec(*.flac)" Comment="A free, open source codec for lossless audio compression and decompression" />
        <ProfileLnk ID="10001100" Name="MKA(Matroska) Audio(*.mka)" Comment="Audio format,it is used MKV audio format" />
    </Category>
    <Category ID="1100023" Name="Copy">
        <ProfileLnk ID="10001371" Name="Directly Copy" Comment="Directly files to disk" />
    </Category>
    <Category ID="1100001" Name="iPod">
        <ProfileLnk ID="10001119" Name="iPod (320*240) MPEG-4 Excellent(*.mp4)" Comment="MPEG-4 Video profile optimized for iPod Video(320*240,high quality)" />
        <ProfileLnk ID="10001120" Name="iPod (320*240) MPEG-4 Normal(*.mp4)" Comment="MPEG-4 Video profile optimized for iPod Video(320*240,standard)" />
        <ProfileLnk ID="10001121" Name="iPod Video2 (640*480) MPEG-4 Excellent(*.mp4)" Comment="MPEG-4 Video profile optimized for iPod Video 2(640*480,high quality)" />
        <ProfileLnk ID="10001122" Name="iPod Video2 (640*480) MPEG-4 Normal(*.mp4)" Comment="MPEG-4 Video profile optimized for iPod Video 2(640*480,standard)" />
        <ProfileLnk ID="10001123" Name="iPod Video2 for TV(*.mp4)" Comment="iPod 2 Video for TV out format" />
        <ProfileLnk ID="10001124" Name="iPod (320*240) H.264(*.mp4)" Comment="h.264 Video profile optimized for iPod Video(320*240,high quality)" />
        <ProfileLnk ID="10001125" Name="iPod (640*480) H.264(*.mp4)" Comment="H.264 Video profile optimized for iPod Video(640*480,high quality)" />
        <ProfileLnk ID="10001001" Name="iPod Video MPEG-4(*.mp4)" Comment="MPEG-4 Video profile optimized for iPod Video,iPod Video2" />
        <ProfileLnk ID="10001002" Name="iPod Video H.264(*.mp4)" Comment="H.264 Video profile optimized for iPod Video" />
        <ProfileLnk ID="10001003" Name="iPod Touch MPEG-4(*.mp4)" Comment="Optional Video profile optimized for iPod Touch,iPod Touch 2G" />
        <ProfileLnk ID="10001004" Name="iPod Touch 2 H.264 640x480(*.mp4)" Comment="H.264 Video  profile optimized for iPod Touch 2G" />
        <ProfileLnk ID="10001005" Name="iPod Touch 2 MPEG-4 640x480(*.mp4)" Comment="MPEG-4 Video  profile optimized for iPod Touch 2G" />
        <ProfileLnk ID="10001006" Name="iPod Touch 2 640x480(*.mov)" Comment="Apple QuickTime format optimized for iPod Touch 2G" />
        <ProfileLnk ID="10001007" Name="iPod Touch 2 640x480(*.m4v)" Comment="MPEG-4 Video profile optimized for iPod Touch 2G" />
        <ProfileLnk ID="10001008" Name="iPod Touch 2(640*480) for TV(*.mp4)" Comment="iPod Touch 2 Video for TV Out format(480p)" />
        <ProfileLnk ID="10001009" Name="iPod Touch 2(768*576) for TV(*.mp4)" Comment="iPod Touch 2 Video for TV Out format(576p)" />
        <ProfileLnk ID="10001010" Name="iPod Nano MPEG-4(*.mp4)" Comment="MPEG-4 Video profile optimized for iPod Nano,iPod nano chromatic" />
        <ProfileLnk ID="10001011" Name="iPod Nano 4 H.264 640x480(*.mp4)" Comment="H.264 Video profile optimized for iPod nano chromatic" />
        <ProfileLnk ID="10001012" Name="iPod Nano 4 MPEG-4 640x480(*.mp4)" Comment="MPEG-4 Video profile optimized for iPod nano chromatic" />
        <ProfileLnk ID="10001013" Name="iPod Nano 4 640x480(*.mov)" Comment="Apple QuickTime format optimized for iPod nano chromatic" />
        <ProfileLnk ID="10001014" Name="iPod Nano 4 640x480(*.m4v)" Comment="MPEG-4 Video profile optimized for iPod nano chromatic" />
        <ProfileLnk ID="10001015" Name="iPod Classic MPEG-4(*.mp4)" Comment="Optional Video profile optimized for iPod Classic" />
    </Category>
    <Category ID="1100002" Name="iPhone">
        <ProfileLnk ID="10001134" Name="iPhone MPEG-4 480x320(*.mp4)" Comment="MPEG-4 Video profile optimized for iPhone(480*320)" />
        <ProfileLnk ID="10001135" Name="iPhone H.264 480x320(*.mp4)" Comment="H.264 Video profile optimized for iPhone(480*320)" />
        <ProfileLnk ID="10001136" Name="iPhone MPEG-4 640x480(*.mp4)" Comment="MPEG-4 Video profile optimized for iPhone(640*480)" />
        <ProfileLnk ID="10001137" Name="iPhone H.264 640x480(*.mp4)" Comment="H.264 Video profile optimized for iPhone(640*480,high quality)" />
        <ProfileLnk ID="10001139" Name="iPhone 3G MPEG-4 480x320(*.mp4)" Comment="MPEG-4 Video profile optimized for iPhone 3G(480*320)" />
        <ProfileLnk ID="10001140" Name="iPhone 3G H.264 480x320(*.mp4)" Comment="H.264 Video profile optimized for iPhone 3G(480*320,high quality)" />
        <ProfileLnk ID="10001141" Name="iPhone 3G MPEG-4 640x480(*.mp4)" Comment="MPEG-4 Video profile optimized for iPhone 3G(640*480)" />
        <ProfileLnk ID="10001142" Name="iPhone 3G H.264 640x480(*.mp4)" Comment="H.264 Video profile optimized for iPhone 3G(640*480,high quality)" />
        <ProfileLnk ID="10001016" Name="iPhone Video MPEG-4(*.mp4)" Comment="Optional Video profile optimized for iPhone" />
        <ProfileLnk ID="10001017" Name="iPhone 3G Video MPEG-4(*.mp4)" Comment="Optional Video profile optimized for iPhone 3G" />
        <ProfileLnk ID="10001018" Name="iPhone 3G MOV 640 x 480(*.mov)" Comment="Apple QuickTime format for iPhone 3G" />
        <ProfileLnk ID="10001370" Name="iPhone Ringtones (*.m4r)" Comment="iPhone Ringtones AAC Audio" />
    </Category>
    <Category ID="1100003" Name="Apple TV">
        <ProfileLnk ID="10001019" Name="Apple TV MPEG-4 512x384(*.mp4)" Comment="MPEG-4 Video profile optimized for Apple TV(512x384)" />
        <ProfileLnk ID="10001020" Name="Apple TV MPEG-4 720x432(*.mp4)" Comment="MPEG-4 Video profile optimized for Apple TV(720x432)" />
        <ProfileLnk ID="10001021" Name="Apple TV H.264 720x480(*.mp4)" Comment="H.264 Video profile optimized for Apple TV(720x480)" />
        <ProfileLnk ID="10001022" Name="Apple TV H.264 1280x720(*.mp4)" Comment="H.264 Video profile optimized for Apple TV(1280x720)" />
        <ProfileLnk ID="10001382" Name="Apple TV H.264 AC3 720x480(*.mp4)" Comment="H.264 Video with AC3 Audio profile optimized for Apple TV(720x480)" />
        <ProfileLnk ID="10001383" Name="Apple TV H.264 AC3 1280x720(*.mp4)" Comment="H.264 Video with AC3 Audio profile optimized for Apple TV(1280x720)" />
    </Category>
    <Category ID="1100004" Name="PSP/PS3">
        <ProfileLnk ID="10001152" Name="PSP - PSP MPEG-4 Video(*.mp4)" Comment="MPEG-4 Video profile optimized for Sony PSP(standard)" />
        <ProfileLnk ID="10001153" Name="PSP - PSP MPEG-4 Video Excellent Quailty(*.mp4)" Comment="MPEG-4 Video profile optimized for Sony PSP(high quality)" />
        <ProfileLnk ID="10001154" Name="PSP - PSP MPEG-4 Video minimal Size(*.mp4)" Comment="MPEG-4 Video profile optimized for Sony PSP(fast conversion speed)" />
        <ProfileLnk ID="10001156" Name="PSP H.264 Movie(*.mp4)" Comment="H.264 Video profile optimized for PSP 1000,PSP 2000,PSP 3000" />
        <ProfileLnk ID="10001023" Name="PSP Video MPEG-4(*.mp4)" Comment="MPEG-4 Video profile optimized for PSP 1000,PSP 2000" />
        <ProfileLnk ID="10001024" Name="PSP AVC Video Format(*.mp4)" Comment="H.264 Video profile optimized for Sony PSP" />
        <ProfileLnk ID="10001025" Name="PS3 Video(480P) MPEG-4(*.mp4)" Comment="H.264 Video profile optimized for Sony PS3(480P)" />
        <ProfileLnk ID="10001026" Name="PS3 Video(720P) MPEG-4(*.mp4)" Comment="H.264 Video profile optimized for Sony PS3(720P)" />
        <ProfileLnk ID="10001027" Name="PS3 Video(1080P) MPEG-4(*.mp4)" Comment="H.264 Video profile optimized for Sony PS3(1080P)" />
        <ProfileLnk ID="10001028" Name="PSP 3000 Video MPEG-4(*.mp4)" Comment="MPEG-4 Video profile optimized for PSP 3000" />
        <ProfileLnk ID="10001029" Name="PSP 3000 Video H.264(*.mp4)" Comment="H.264 Video profile optimized for PSP 3000" />
        <ProfileLnk ID="10001384" Name="PS3 H.264 AC3 MPEG-4(*.mp4)" Comment="H.264 Video with AC3 Audio profile optimized for Sony PS3" />
    </Category>
    <Category ID="1100005" Name="Gphone">
        <ProfileLnk ID="10001037" Name="Gphone Video MPEG-4(*.mp4)" Comment="MPEG-4 Video profile optimized for Gphone" />
        <ProfileLnk ID="10001038" Name="Gphone Video H.264(*.mp4)" Comment="H.264 Video profile optimized for Gphone" />
        <ProfileLnk ID="10001040" Name="Gphone Video WMV(*.wmv)" Comment="WMV Video profile optimized for Gphone" />
    </Category>
    <Category ID="1100006" Name="BlackBerry">
        <ProfileLnk ID="10001209" Name="BlackBerry 8800(*.avi)" Comment="AVI Video profile optimized for BlackBerry 8800" />
        <ProfileLnk ID="10001210" Name="BlackBerry 8820(*.avi)" Comment="AVI Video profile optimized for BlackBerry 8820" />
        <ProfileLnk ID="10001211" Name="BlackBerry 8830(*.avi)" Comment="AVI Video profile optimized for BlackBerry 8830" />
        <ProfileLnk ID="10001212" Name="BlackBerry 8300(*.avi)" Comment="AVI Video profile optimized for BlackBerry 8300" />
        <ProfileLnk ID="10001213" Name="BlackBerry 8310(*.avi)" Comment="AVI Video profile optimized for BlackBerry 8310" />
        <ProfileLnk ID="10001214" Name="BlackBerry 8100(*.avi)" Comment="AVI Video profile optimized for BlackBerry 8100" />
        <ProfileLnk ID="10001215" Name="BlackBerry 8130(*.avi)" Comment="AVI Video profile optimized for BlackBerry 8130" />
        <ProfileLnk ID="10001218" Name="BlackBerry MP4 series(*.mp4)" Comment="MPEG-4 Video profile optimized for BlackBerry series" />
        <ProfileLnk ID="10001031" Name="BlackBerry Storm series(*.mp4)" Comment="MP4 Video profile optimized for BlackBerry Storm series" />
        <ProfileLnk ID="10001033" Name="BlackBerry Bold 9000(*.mp4)" Comment="MP4 Video profile optimized for BlackBerry Bold 9000" />
        <ProfileLnk ID="10001035" Name="BlackBerry AVI series(*.avi)" Comment="AVI Video profile optimized for BlackBerry series" />
        <ProfileLnk ID="10001036" Name="BlackBerry 3GP series(*.3gp)" Comment="3GP Video profile optimized for BlackBerry series" />
        <ProfileLnk ID="10001032" Name="BlackBerry Storm series(*.wmv)" Comment="WMV Video profile optimized for BlackBerry Storm series" />
        <ProfileLnk ID="10001034" Name="BlackBerry Bold 9000(*.wmv)" Comment="WMV Video profile optimized for BlackBerry Bold 9000" />
        <ProfileLnk ID="10001219" Name="BlackBerry WMV series(*.wmv)" Comment="WMV Video profile optimized for BlackBerry series" />
        <ProfileLnk ID="10001221" Name="BlackBerry M4A Audio(*.m4a)" Comment="M4A audio profile optimized for BlackBerry series" />
    </Category>
    <Category ID="1100007" Name="3GP">
        <ProfileLnk ID="10001063" Name="Mobile Phone Video - 3GP(*.3gp)" Comment="Multimedia h.263 coding format used in mobile terminals" />
        <ProfileLnk ID="10001064" Name="Mobile Phone Video - 3GPP(*.3g2)" Comment="Multimedia xvid coding format used in mobile terminals" />
        <ProfileLnk ID="10001065" Name="3rd Generation Partnership Project - 3GP(*.3gp)" Comment="3GP(3rd Generation Partnership Project)Multimedia format" />
        <ProfileLnk ID="10001066" Name="3rd Generation Partnership Project 2 - 3GPP(*.3g2)" Comment="3GPP(3rd Generation Partnership Project 2)Multimedia format" />
    </Category>
    <Category ID="1100008" Name="VOB Format">
        <ProfileLnk ID="10001078" Name="DVD-Video Format - NTSC(*.vob)" Comment="DVD Video profile optimized for television system of NTSC" />
        <ProfileLnk ID="10001079" Name="DVD-Video Format - PAL(*.vob)" Comment="DVD Video profile optimized for television system of PAL" />
        <ProfileLnk ID="10001080" Name="DVD-Video Format - SECAM(*.vob)" Comment="DVD Video profile optimized for television system of SECAM" />
    </Category>
    <Category ID="1100009" Name="HD Video">
        <ProfileLnk ID="10001086" Name="H.264 HD Video(*.mp4)" Comment="H.264 Video with HD Standards" />
        <ProfileLnk ID="10001088" Name="H.264 HD Video(*.mov)" Comment="Apple&apos;s QuickTime Video with HD Standards" />
        <ProfileLnk ID="10001087" Name="MPEG-4 HD Video(*.mp4)" Comment="MPEG-4 Video with HD Standards" />
        <ProfileLnk ID="10001089" Name="MPEG-2 HD Video(*.mpg)" Comment="MPEG-2 Video with HD Standards" />
        <ProfileLnk ID="10001328" Name="MPEG-TS HD Video(*.ts)" Comment="A type of digital container HD format,with high quality" />
        <ProfileLnk ID="10001326" Name="MKV HD Video (*.mkv)" Comment="Matroska Video with HD Standards" />
        <ProfileLnk ID="10001329" Name="WMV HD(*.wmv)" Comment="WMV Video with HD Standards" />
        <ProfileLnk ID="10001331" Name="DivX HD(*.avi)" Comment="DivX Video with HD Standards" />
        <ProfileLnk ID="10001085" Name="AVI HD Video(*.avi)" Comment="AVI (Audio Video Interleave) with HD Standards" />
        <ProfileLnk ID="10001385" Name="H.264 AC3 HD Video(*.mp4)" Comment="H.264 Video AC3 Audio with HD Standards" />
        <ProfileLnk ID="10001386" Name="H.264 AC3 HD Video(*.mov)" Comment="Apple&apos;s QuickTime Video AC3 Audio with HD Standards" />
    </Category>
    <Category ID="1100010" Name="Flash Video">
        <ProfileLnk ID="10001045" Name="FLV-Flash Video Format(*.flv)" Comment="Widely used network Video streaming media format(Flash Video Files)" />
        <ProfileLnk ID="10001332" Name="FLV  H.264 (*.flv)" Comment="Flash video with H.264 and aac codec" />
        <ProfileLnk ID="10001333" Name="F4V (*.f4v)" Comment="A kind of HD flash video format coding with H.264" />
        <ProfileLnk ID="10001046" Name="SWF-SWF Format(*.swf)" Comment="Multimedia format,widely used for web page" />
    </Category>
    <Category ID="1100011" Name="Mobile Device">
        <ProfileLnk ID="10001226" Name="Pocket PC(*.avi)" Comment="AVI Video profile optimized for Pocket PC" />
        <ProfileLnk ID="10001227" Name="Pocket PC VGA(*.avi)" Comment="AVI Video profile optimized for Pocket PC VGA" />
        <ProfileLnk ID="10001237" Name="Sony Ericsson W810c(*.3gp)" Comment="3GP Video profile optimized for Sony Ericsson W810c" />
        <ProfileLnk ID="10001238" Name="Sony Ericsson S500C(*.3gp)" Comment="3GP Video profile optimized for Sony Ericsson S500C" />
        <ProfileLnk ID="10001239" Name="Sony Ericsson K818c(*.3gp)" Comment="3GP Video profile optimized for Sony Ericsson K818c" />
        <ProfileLnk ID="10001240" Name="Sony Ericsson W830c(*.3gp)" Comment="3GP Video profile optimized for Sony Ericsson W830c" />
        <ProfileLnk ID="10001241" Name="Sony Ericsson 3GP series(*.3gp)" Comment="3GP Video profile optimized for Sony Ericsson series" />
        <ProfileLnk ID="10001242" Name="Sony Ericsson MPEG4 series(*.mp4)" Comment="MPEG-4 Video profile optimized for Sony Ericsson series" />
        <ProfileLnk ID="10001044" Name="Sony Walkman Video(*.mp4)" Comment="MPEG-4 Video profile optimized for Sony Walkman" />
        <ProfileLnk ID="10001243" Name="Samsung SGH-E848(*.3gp)" Comment="3GP Video profile optimized for Samsung SGH-E848" />
        <ProfileLnk ID="10001244" Name="Samsung SGH-E908(*.3gp)" Comment="3GP Video profile optimized for Samsung SGH-E908" />
        <ProfileLnk ID="10001245" Name="Samsung SGH-D828(*.3gp)" Comment="3GP Video profile optimized for Samsung SGH-D828" />
        <ProfileLnk ID="10001246" Name="Samsung SGH-F308(*.3gp)" Comment="3GP Video profile optimized for Samsung SGH-F308" />
        <ProfileLnk ID="10001247" Name="Samsung 3GP series(*.3gp)" Comment="3GP Video profile optimized for Samsung series" />
        <ProfileLnk ID="10001248" Name="Samsung MPEG4 series(*.mp4)" Comment="MPEG-4 Video profile optimized for Samsung series" />
        <ProfileLnk ID="10001249" Name="Motorola RAZR2 V8(*.3gp)" Comment="3GP Video profile optimized for Motorola RAZR2 V8" />
        <ProfileLnk ID="10001250" Name="Motorola A1200(*.3gp)" Comment="3GP Video profile optimized for Motorola A1200" />
        <ProfileLnk ID="10001251" Name="Motorola ROKR E6(*.3gp)" Comment="3GP Video profile optimized for Motorola ROKR E6" />
        <ProfileLnk ID="10001252" Name="Motorola Q8(*.3gp)" Comment="3GP Video profile optimized for Motorola Q8" />
        <ProfileLnk ID="10001253" Name="Motorola 3GP series(*.3gp)" Comment="3GP Video profile optimized for Motorola series" />
        <ProfileLnk ID="10001254" Name="LG KG70(*.3gp)" Comment="3GP Video profile optimized for LG KG70" />
        <ProfileLnk ID="10001255" Name="LG KU990(*.mp4)" Comment="MPEG-4 Video profile optimized for LG KU990" />
        <ProfileLnk ID="10001256" Name="LG Prada KE850(*.mp4)" Comment="MPEG-4 Video profile optimized for LG Prada KE850" />
        <ProfileLnk ID="10001257" Name="LG KE970(*.mp4)" Comment="MPEG-4 Video profile optimized for LG KE970" />
        <ProfileLnk ID="10001258" Name="LG 3GP series(*.3gp)" Comment="3GP Video profile optimized for LG series" />
        <ProfileLnk ID="10001259" Name="LG MPEG4 series(*.mp4)" Comment="MPEG-4 Video profile optimized for LG series" />
        <ProfileLnk ID="10001042" Name="Palm Pre Video MPEG-4(*.mp4)" Comment="MP4 Video profile optimized for Palm Pre" />
        <ProfileLnk ID="10001043" Name="Palm Pre Video H.263(*.3gp)" Comment="3GP h.263 Video profile optimized for Palm Pre" />
        <ProfileLnk ID="10001041" Name="Palm Pre Video WMV(*.wmv)" Comment="WMV Video profile optimized for Palm Pre" />
    </Category>
    <Category ID="1100013" Name="Windows mobile">
        <ProfileLnk ID="10001060" Name="Dell Player Video(*.wmv)" Comment="Windows Media Video profile optimized for Dell Player" />
        <ProfileLnk ID="10001061" Name="HP iPAQ Video(*.wmv)" Comment="Windows Media Video profile optimized for HP IPAQ" />
        <ProfileLnk ID="10001062" Name="General Pocket PC Video(*.wmv)" Comment="Windows Media Video profile optimized for Pocket PC" />
        <ProfileLnk ID="10001334" Name="iRiver Video(*.wmv)" Comment="WMV Video profile optimized for iRiver" />
    </Category>
    <Category ID="1100014" Name="Zune/Xbox 360 Device">
        <ProfileLnk ID="10001372" Name="Zune HD MP4 Video(*.mp4)" Comment="MP4 Video for Zune HD" />
        <ProfileLnk ID="10001373" Name="Zune HD WMV Video(*.wmv)" Comment="WMV Video for Zune HD" />
        <ProfileLnk ID="10001058" Name="Zune 2 (640*480) MPEG-4 Video(*.mp4)" Comment="MPEG-4 Video profile optimized for Microsoft Zune 2(640*480)" />
        <ProfileLnk ID="10001056" Name="Zune Video - Windows Media Video(*.wmv)" Comment="Windows Media Video format optimized for Microsoft Zune" />
        <ProfileLnk ID="10001057" Name="Zune 2 Video - Windows Media Video(*.wmv)" Comment="Windows Media Video format optimized for micorsoft Zune 2" />
        <ProfileLnk ID="10001059" Name="Xbox 360 Video - Windows Media Video(*.wmv)" Comment="Windows Media Video profile optimized for Xbox 360" />
        <ProfileLnk ID="10001260" Name="Xbox 360 Video (640*480)(*.wmv)" Comment="Optimized Video configure for Xbox 360 Video (640*480)" />
    </Category>
    <Category ID="1100015" Name="Creative ZEN">
        <ProfileLnk ID="10001049" Name="ZEN Player Video(*.wmv)" Comment="Windows Media Video format optimized for some Creative ZEN Player" />
        <ProfileLnk ID="10001047" Name="Creative ZEN Player Video(*.avi)" Comment="AVI Video profile optimized for some Creative Zen Player such as  Zen W" />
        <ProfileLnk ID="10001050" Name="ZEN Player MPEG-1 Video (*.mpg)" Comment="MPEG-1 Video profile optimized for some Creative Zen Players" />
        <ProfileLnk ID="10001051" Name="ZEN Player MPEG-2 Video (*.mpg)" Comment="MPEG-2 Video profile optimized for some Creative Zen Players" />
        <ProfileLnk ID="10001052" Name="ZEN Player MPEG-4 Video (*.mp4)" Comment="MPEG-4 Video profile optimized for some Creative Zen Players" />
    </Category>
    <Category ID="1100016" Name="Archos">
        <ProfileLnk ID="10001054" Name="Archos Player Video(*.avi)" Comment="AVI Video profile optimized for some Archos player" />
        <ProfileLnk ID="10001303" Name="Archos 5/7 AVI Video(*.avi)" Comment="AVI Video profile optimized for Archos 5/7" />
        <ProfileLnk ID="10001304" Name="Archos 5/7 WMV Video(*.wmv)" Comment="WMV Video profile optimized for Archos 5/7" />
        <ProfileLnk ID="10001305" Name="Archos 605/704/705 AVI Video(*.avi)" Comment="AVI Video profile optimized for Archos 605/704/705" />
        <ProfileLnk ID="10001306" Name="Archos 605/704/705 WMV Video(*.wmv)" Comment="WMV Video profile optimized for Archos 605/704/705" />
        <ProfileLnk ID="10001307" Name="Archos 504/604 AVI Video(*.avi)" Comment="AVI Video profile optimized for Archos 504/604" />
        <ProfileLnk ID="10001308" Name="Archos 504/604 WMV Video(*.wmv)" Comment="WMV Video profile optimized for Archos 504/604" />
        <ProfileLnk ID="10001309" Name="Archos 404/405 AVI Video(*.avi)" Comment="AVI Video profile optimized for Archos 404/405" />
        <ProfileLnk ID="10001310" Name="Archos 404/405 WMV Video(*.wmv)" Comment="WMV Video profile optimized for Archos 404/405" />
        <ProfileLnk ID="10001311" Name="Archos AV500/AV700 AVI Video(*.avi)" Comment="AVI Video profile optimized for Archos AV500/AV700" />
        <ProfileLnk ID="10001312" Name="Archos AV500/AV700 WMV Video(*.wmv)" Comment="WMV Video profile optimized for Archos AV500/AV700" />
        <ProfileLnk ID="10001313" Name="Archos 105 WMV Video(*.wmv)" Comment="WMV Video profile optimized for Archos 105" />
    </Category>
    <Category ID="1100020" Name="Nokia">
        <ProfileLnk ID="10001229" Name="Nokia MP4 series(*.mp4)" Comment="MPEG-4 Video profile optimized for Nokia series" />
        <ProfileLnk ID="10001230" Name="Nokia FLV series(*.flv)" Comment="FLV Video profile optimized for Nokia series" />
        <ProfileLnk ID="10001231" Name="Nokia WMV series(*.wmv)" Comment="WMV Video profile optimized for Nokia series" />
        <ProfileLnk ID="10001233" Name="Nokia M4A Audio(*.m4a)" Comment="MPEG-4 Audio profile optimized for Nokia series" />
        <ProfileLnk ID="10001234" Name="Nokia MP3 Audio(*.mp3)" Comment="MPEG Layer-3 Audio profile optimized for Nokia series" />
        <ProfileLnk ID="10001235" Name="Nokia WAV Audio(*.wav)" Comment="Waveform Audio profile optimized for Nokia series" />
    </Category>
    <Category ID="1100017" Name="PowerPoint">
        <ProfileLnk ID="10001335" Name="WMV-2(*.wmv)" Comment="WMV Video for PowerPoint" />
        <ProfileLnk ID="10001336" Name="MPEG-1(*.mpg)" Comment="MPEG-1 Video for PowerPoint" />
    </Category>
    <Category ID="1100018" Name="Adobe Premiere/Sony Vegas">
        <ProfileLnk ID="10001337" Name="WMV (VC-1) (*.wmv)" Comment="WMV Video for NLE (non linear edition)" />
        <ProfileLnk ID="10001338" Name="MPEG-2 (*.mpg)" Comment="MPEG-2 Video for NLE (non linear edition)" />
        <ProfileLnk ID="10001339" Name="MOV (AVC)(*.mov)" Comment="H.264 MOV Video for NLE (non linear edition)" />
    </Category>
    <!--
  mac:
  Final Cut/iMovie - Mac
  MP4 (AVC)
-->
    <Category ID="1100021" Name="Lossless raw video">
        <ProfileLnk ID="10001352" Name="BGR24 (*.avi)" Comment="Raw Video with BGR24 format" />
        <ProfileLnk ID="10001353" Name="RGB555 (*.avi)" Comment="Raw Video with RGB555 format" />
        <ProfileLnk ID="10001354" Name="YUY2 (*.avi)" Comment="Raw Video with YUY2 format" />
        <ProfileLnk ID="10001356" Name="RGBA32 (*.avi)" Comment="Raw Video with RGBA32 format" />
    </Category>
    <Category ID="1100019" Name="Remux">
        <ProfileLnk ID="10001340" Name="AVI Video Remux(*.avi)" Comment="Directly remux to AVI format" />
        <ProfileLnk ID="10001341" Name="MP4 Video Remux(*.mp4)" Comment="Directly remux to MP4 format" />
        <ProfileLnk ID="10001342" Name="MOV Video Remux(*.mov)" Comment="Directly remux to MOV format" />
        <ProfileLnk ID="10001343" Name="MPEG-PS Video Remux(*.mpg)" Comment="Directly remux to MPEG-PS format" />
        <ProfileLnk ID="10001344" Name="MPEG-TS Video Remux(*.ts)" Comment="Directly remux to MPEG-TS format" />
        <ProfileLnk ID="10001348" Name="DTS Video Remux(*.dts)" Comment="Directly remux to DTS format" />
        <ProfileLnk ID="10001349" Name="FLV Video Remux(*.flv)" Comment="Directly remux to FLV format" />
        <ProfileLnk ID="10001350" Name="WMV Video Remux(*.wmv)" Comment="Directly remux to WMV format" />
        <ProfileLnk ID="10001351" Name="3GP Video Remux(*.3gp)" Comment="Directly remux to 3GP format" />
        <ProfileLnk ID="10001345" Name="MP3 Audio Remux(*.mp3)" Comment="Directly remux to MP3 format" />
        <ProfileLnk ID="10001346" Name="AAC Audio Remux(*.aac)" Comment="Directly remux to AAC format" />
        <ProfileLnk ID="10001347" Name="AC3 Audio Remux(*.ac3)" Comment="Directly remux to AC3 format" />
    </Category>
    <Category ID="1100022" Name="VCD/DVD/SVCD">
        <ProfileLnk ID="10001361" Name="VCD PAL (16:9)" Comment="VCD PAL (16:9) 352*288 (*.mpg)" />
        <ProfileLnk ID="10001362" Name="VCD NTSC (16:9)" Comment="VCD NTSC (16:9) 352*240 (*.mpg)" />
        <ProfileLnk ID="10001363" Name="VCD PAL (4:3)" Comment="VCD PAL (4:3) 352*288 (*.mpg)" />
        <ProfileLnk ID="10001365" Name="VCD NTSC (4:3)" Comment="VCD NTSC (4:3) 352*240 (*.mpg)" />
        <ProfileLnk ID="10001366" Name="DVD PAL (16:9)" Comment="DVD PAL (16:9) 720*576 (*.vob)" />
        <ProfileLnk ID="10001367" Name="DVD NTSC (16:9)" Comment="DVD NTSC (16:9) 720*480 (*.vob)" />
        <ProfileLnk ID="10001368" Name="DVD PAL (4:3)" Comment="DVD PAL (4:3) 720*576 (*.vob)" />
        <ProfileLnk ID="10001369" Name="DVD NTSC (4:3)" Comment="DVD NTSC (4:3) 720*480 (*.vob)" />
        <ProfileLnk ID="10001357" Name="SVCD PAL (16:9)" Comment="SVCD PAL (16:9) 480*576 (*.vob)" />
        <ProfileLnk ID="10001358" Name="SVCD NTSC (16:9)" Comment="SVCD NTSC (16:9) 480*480 (*.vob)" />
        <ProfileLnk ID="10001359" Name="SVCD PAL (4:3)" Comment="SVCD PAL (4:3) 480*576 (*.vob)" />
        <ProfileLnk ID="10001360" Name="SVCD NTSC (4:3)" Comment="SVCD NTSC (4:3) 480*480 (*.vob)" />
    </Category>
    <Category ID="1100024" Name="DV">
        <ProfileLnk ID="10001374" Name="DV AVI NTSC (*.avi)" Comment="DV Video NTSC 720*480" />
        <ProfileLnk ID="10001375" Name="DV AVI PAL (*.avi)" Comment="DV Video PAL 720*576" />
        <ProfileLnk ID="10001376" Name="Apple DV NTSC (*.dv)" Comment="Apple DV Video NTSC 720*480" />
        <ProfileLnk ID="10001377" Name="Apple DV PAL (*.dv)" Comment="Apple DV Video PAL 720*576" />
    </Category>
    <Category ID="1100025" Name="Wii">
        <ProfileLnk ID="10001378" Name="Wii MOV Video(*.mov)" Comment="Wii mov format with mjpeg support" />
        <ProfileLnk ID="10001379" Name="Wii AVI Video(*.avi)" Comment="Wii avi format with mjpeg support" />
        <ProfileLnk ID="10001380" Name="Wii M4A Audio(*.m4a)" Comment="Wii m4a audio format" />
        <ProfileLnk ID="10001381" Name="Wii MP3 Audio(*.mp3)" Comment="Wii mp3 audio format" />
    </Category>
</ProfileLib>
