<?xml version="1.0" encoding="UTF-8" ?>
<Profile DefID="10001379" DefName="Wii AVI Video(*.avi)" DeviceName="none" Enabled="1" DefType="0"  Comment="Wii avi format with mjpeg support">
    <Parameter FileExt=".avi" Format="avi" ExporterName="FFExporter" AVInclude="0" AVNeed="0" AVStyle="0">
        <AudioParam AudioCodecName="pcm_s16le" AudioBitrate="0" Samplerate="48000" Channel="2" />
        <VideoParam VideoCodecName="mjpeg" Tolerance="4000" Width="720" Height="480" FrameRate="29.970000" VideoBitrate="6000" />
    </Parameter>
    <ColItem>
        <AudioCodecName DefID="0" DefValue="pcm_s16le" />
        <AudioBitrate DefID="0" DefValue="0" />
        <SampleRate DefID="3" DefValue="22050,32000,44100,48000,8000" />
        <Channel DefID="1" DefValue="1,2" />
        <VideoCodecName DefID="0" DefValue="mjpeg,msmpeg4" />
        <Size DefID="2" DefValue="original,640*480,720*480,720*576" />
        <FrameRate DefID="1" DefValue="25,29.97" />
        <VideoBitrate DefID="5" DefValue="original,2000,3000,4000,5000,6000" />
    </ColItem>
</Profile>
